contuino_core/__init__.py
contuino_core/core.py
contuino_core/default_actions.py
contuino_core-0.1.5.dev0.dist-info/LICENSE
contuino_core-0.1.5.dev0.dist-info/METADATA
contuino_core-0.1.5.dev0.dist-info/WHEEL
contuino_core-0.1.5.dev0.dist-info/top_level.txt
contuino_core-0.1.5.dev0.dist-info/RECORD
