Metadata-Version: 2.1
Name: contuino-core
Version: 0.1.5.dev0
Summary: Core for contuino server and client.
Home-page: UNKNOWN
Author: Luka Milosevic
Author-email: lukamilosevic.py@gmail.com
License: MIT
Platform: UNKNOWN
Classifier: License :: OSI Approved :: MIT License
Classifier: Programming Language :: Python
Classifier: Programming Language :: Python :: 3
Classifier: Programming Language :: Python :: 3.6
Classifier: Programming Language :: Python :: Implementation :: CPython
Classifier: Programming Language :: Python :: Implementation :: PyPy
Requires-Python: >=3.6.0
